daccuracy/__init__.py
daccuracy/main.py
daccuracy/version.py
daccuracy/cli/main.py
daccuracy/cli/two_d_labeled_slices_to_3d.py
daccuracy/config/csv_.py
daccuracy/config/nicegui.py
daccuracy/config/output.py
daccuracy/constant/input.py
daccuracy/constant/measures.py
daccuracy/constant/nicegui.py
daccuracy/constant/project.py
daccuracy/constant/two_d_labeled_slices_to_3d.py
daccuracy/hint/csv_.py
daccuracy/hint/input.py
daccuracy/hint/measures.py
daccuracy/interface/console/main.py
daccuracy/interface/console/two_d_labeled_slices_to_3d.py
daccuracy/interface/storage/csv_.py
daccuracy/interface/storage/input.py
daccuracy/interface/storage/output.py
daccuracy/interface/window/pypl.py
daccuracy/nicegui/main.py
daccuracy/task/image.py
daccuracy/task/measures.py
daccuracy/type/measures.py
daccuracy-2025.1.dist-info/METADATA
daccuracy-2025.1.dist-info/WHEEL
daccuracy-2025.1.dist-info/entry_points.txt
daccuracy-2025.1.dist-info/top_level.txt
daccuracy-2025.1.dist-info/RECORD
