Metadata-Version: 2.4
Name: daccuracy
Version: 2025.1
Summary: Detection and Segmentation Accuracy Measures
Home-page: https://src.koda.cnrs.fr/eric.debreuve/daccuracy/
Author: Eric Debreuve
Author-email: eric.debreuve@cnrs.fr
License: CeCILL-2.1
Project-URL: Documentation, https://src.koda.cnrs.fr/eric.debreuve/daccuracy/-/wikis/home
Project-URL: Source, https://src.koda.cnrs.fr/eric.debreuve/daccuracy/
Keywords: image,object detection,segmentation,accuracy
Classifier: Topic :: Scientific/Engineering :: Image Recognition
Classifier: Intended Audience :: Science/Research
Classifier: License :: OSI Approved :: CEA CNRS Inria Logiciel Libre License, version 2.1 (CeCILL-2.1)
Classifier: Programming Language :: Python :: 3
Classifier: Development Status :: 5 - Production/Stable
Requires-Python: >=3.9
Requires-Dist: matplotlib
Requires-Dist: nicegui
Requires-Dist: numpy
Requires-Dist: pillow
Requires-Dist: scikit-image
Requires-Dist: scipy
Dynamic: author
Dynamic: author-email
Dynamic: classifier
Dynamic: description
Dynamic: description-content-type
Dynamic: home-page
Dynamic: keywords
Dynamic: license
Dynamic: project-url
Dynamic: requires-dist
Dynamic: requires-python
Dynamic: summary
